cd/code.py
cd/util.py
fs/file.py
poorkit.py
video/video.py
poorkit-0.0.11.dist-info/entry_points.txt
poorkit-0.0.11.dist-info/LICENSE
poorkit-0.0.11.dist-info/METADATA
poorkit-0.0.11.dist-info/WHEEL
poorkit-0.0.11.dist-info/RECORD
