Metadata-Version: 2.1
Name: poorkit
Version: 0.0.11
Summary: A programmer's personal tool collection.
Home-page: https://github.com/huxulm/poorkit
License: MIT
Author: Huxulm
Author-email: huxulm@gmail.com
Requires-Python: >=3.12,<4.0
Classifier: License :: OSI Approved :: MIT License
Classifier: Programming Language :: Python :: 3
Classifier: Programming Language :: Python :: 3.12
Classifier: Programming Language :: Python :: 3.13
Requires-Dist: click (>=8.1.7,<9.0.0)
Requires-Dist: setuptools (>=75.8.0,<76.0.0)
